cdk_pigeon/core/__init__.py
cdk_pigeon/core/py.typed
cdk_pigeon/core/_jsii/__init__.py
cdk_pigeon/core/_jsii/cdk-pigeon@0.1.0.jsii.tgz
cdk_pigeon.core-0.1.0.data/scripts/cdk-pigeon
cdk_pigeon.core-0.1.0.dist-info/LICENSE
cdk_pigeon.core-0.1.0.dist-info/METADATA
cdk_pigeon.core-0.1.0.dist-info/WHEEL
cdk_pigeon.core-0.1.0.dist-info/top_level.txt
cdk_pigeon.core-0.1.0.dist-info/RECORD
