Metadata-Version: 2.1
Name: cdk-pigeon.core
Version: 0.1.0
Summary: AWS Synthetics Canary alternative built for minimal cost 
Home-page: https://github.com/thomasstep/cdk-pigeon.git
Author: Thomas Step<tstep916@gmail.com>
License: Apache-2.0
Project-URL: Source, https://github.com/thomasstep/cdk-pigeon.git
Platform: UNKNOWN
Classifier: Intended Audience :: Developers
Classifier: Operating System :: OS Independent
Classifier: Programming Language :: JavaScript
Classifier: Programming Language :: Python :: 3 :: Only
Classifier: Programming Language :: Python :: 3.6
Classifier: Programming Language :: Python :: 3.7
Classifier: Programming Language :: Python :: 3.8
Classifier: Programming Language :: Python :: 3.9
Classifier: Typing :: Typed
Classifier: Development Status :: 4 - Beta
Classifier: License :: OSI Approved
Requires-Python: >=3.6
Requires-Dist: aws-cdk-lib (<3.0.0,>=2.18.0)
Requires-Dist: constructs (<11.0.0,>=10.0.0)
Requires-Dist: jsii (<2.0.0,>=1.55.1)
Requires-Dist: publication (>=0.0.3)
